dftserialize/__init__.py
dftserialize/deserialize.py
dftserialize/serialize.py
dftserialize-0.2.0.dist-info/LICENSE
dftserialize-0.2.0.dist-info/METADATA
dftserialize-0.2.0.dist-info/WHEEL
dftserialize-0.2.0.dist-info/top_level.txt
dftserialize-0.2.0.dist-info/RECORD
