Metadata-Version: 2.1
Name: dftserialize
Version: 0.2.0
Summary: A next-gen Python object serialization suite using the Discrete Fourier Transform
Home-page: https://github.com/ThePlasmaRailgun/DFTSerialize
Author: Finian Blackett
Author-email: spamsuckersunited@gmail.com
License: UNKNOWN
Platform: UNKNOWN
Classifier: Programming Language :: Python :: 3.6
Classifier: License :: OSI Approved :: GNU General Public License v3 (GPLv3)
Classifier: Operating System :: OS Independent
Requires-Dist: numpy
